mchan/__init__.py
mchan/mchan_functions.py
mchan-0.1.0.dist-info/METADATA
mchan-0.1.0.dist-info/WHEEL
mchan-0.1.0.dist-info/top_level.txt
mchan-0.1.0.dist-info/RECORD
