Metadata-Version: 2.1
Name: mchan
Version: 0.1.0
Summary: test lib
Author: Me
License: MIT
Requires-Dist: pandas
